modrinthpy/__init__.py
modrinthpy/client.py
modrinthpy/decorators.py
modrinthpy/exceptions.py
modrinthpy/models.py
modrinthpy/objects.py
modrinthpy/utils.py
modrinthpy-0.1.0.dist-info/LICENSE
modrinthpy-0.1.0.dist-info/METADATA
modrinthpy-0.1.0.dist-info/WHEEL
modrinthpy-0.1.0.dist-info/top_level.txt
modrinthpy-0.1.0.dist-info/RECORD
