Metadata-Version: 2.1
Name: modrinthpy
Version: 0.1.0
Summary: A Python client for the Modrinth API
Author-email: mrf0rtuna4 <heypers.team@gmail.com>
License: MIT License
Project-URL: Homepage, https://github.com/mrf0rtuna4/modrinthpy
Requires-Python: >=3.6
License-File: LICENSE
Requires-Dist: requests
